mbq/__init__.py
mbq/env/__init__.py
mbq.env-0.0.1.dist-info/DESCRIPTION.rst
mbq.env-0.0.1.dist-info/METADATA
mbq.env-0.0.1.dist-info/RECORD
mbq.env-0.0.1.dist-info/WHEEL
mbq.env-0.0.1.dist-info/metadata.json
mbq.env-0.0.1.dist-info/top_level.txt
mbq.env-0.0.1.dist-info/zip-safe
tests/__init__.py
tests/compat.py
tests/test_env.py
